emd/__init__.py
emd/cfn/codepipeline/template.yaml
emd/cfn/ec2/template.yaml
emd/cfn/ecs/post_build.py
emd/cfn/ecs/template.yaml
emd/cfn/sagemaker_async/post_build.py
emd/cfn/sagemaker_async/template.yaml
emd/cfn/sagemaker_realtime/post_build.py
emd/cfn/sagemaker_realtime/template.yaml
emd/cfn/shared/ecs_cluster.py
emd/cfn/shared/ecs_cluster.yaml
emd/cfn/shared/filter_parameters.py
emd/cfn/shared/openai_router/Dockerfile
emd/cfn/shared/openai_router/go.mod
emd/cfn/shared/openai_router/go.sum
emd/cfn/shared/openai_router/main.go
emd/cfn/shared/vpc.yaml
emd/cli.py
emd/commands/bootstrap.py
emd/commands/config.py
emd/commands/deploy.py
emd/commands/destroy.py
emd/commands/invoke/invoke.py
emd/commands/models.py
emd/commands/status.py
emd/commands/version.py
emd/constants.py
emd/integrations/langchain_clients.py
emd/models/README.md
emd/models/__init__.py
emd/models/asr/__init__.py
emd/models/asr/whisper.py
emd/models/audio/__init__.py
emd/models/audio/higgs_audio.py
emd/models/chat_templates/deepseek_r1.jinja
emd/models/chat_templates/deepseek_r1_distill.jinja
emd/models/chat_templates/internlm2d5_add_prefill_chat_template.jinja
emd/models/chat_templates/llama3d3_add_prefill_chat_templates copy.jinja
emd/models/chat_templates/llama3d3_add_prefill_chat_templates.jinja
emd/models/chat_templates/qwen2vl_add_prefill_chat_template.jinja
emd/models/chat_templates/qwen_2d5_add_prefill_chat_template.jinja
emd/models/chat_templates/qwq_32b_add_prefill_chat_template.jinja
emd/models/comfyui/__init__.py
emd/models/comfyui/comfyui.py
emd/models/custom/__init__.py
emd/models/custom/custom_docker.py
emd/models/embeddings/__init__.py
emd/models/embeddings/bert_embedding.py
emd/models/embeddings/bge_vl.py
emd/models/embeddings/jina.py
emd/models/embeddings/qwen.py
emd/models/engines.py
emd/models/frameworks.py
emd/models/instances.py
emd/models/llms/__init__.py
emd/models/llms/baichuan.py
emd/models/llms/deepseek.py
emd/models/llms/glm.py
emd/models/llms/internlm.py
easy_model_deployer-0.9.47.dist-info/METADATA
easy_model_deployer-0.9.47.dist-info/WHEEL
easy_model_deployer-0.9.47.dist-info/entry_points.txt
easy_model_deployer-0.9.47.dist-info/licenses/LICENSE
easy_model_deployer-0.9.47.dist-info/RECORD
