Metadata-Version: 2.4
Name: easy-model-deployer
Version: 0.9.47
Summary: Easy Model Deployer
License-File: LICENSE
Author: Yi Yan
Author-email: <yiyanz@amazon.com>
Requires-Python: >=3.9,<4.0
Classifier: Programming Language :: Python :: 3
Classifier: Programming Language :: Python :: 3.9
Classifier: Programming Language :: Python :: 3.10
Classifier: Programming Language :: Python :: 3.11
Classifier: Programming Language :: Python :: 3.12
Classifier: Programming Language :: Python :: 3.13
Classifier: Programming Language :: Python :: 3.14
Requires-Dist: boto3 (>=1.35.0,<2.0.0)
Requires-Dist: click (==8.0.4)
Requires-Dist: huggingface-hub (>=0.31.2,<0.32.0)
Requires-Dist: jinja2 (>=3.1.4,<4.0.0)
Requires-Dist: langchain (>=0.3.9,<0.4.0)
Requires-Dist: langchain-aws (>=0.2.13,<0.3.0)
Requires-Dist: modelscope (>=1.21.1,<2.0.0)
Requires-Dist: openai (>=1.54.4,<2.0.0)
Requires-Dist: pydantic (==2.11.4)
Requires-Dist: questionary (>=2.1.0,<3.0.0)
Requires-Dist: requests (>=2.32,<3.0)
Requires-Dist: rich (==14.0.0)
Requires-Dist: sagemaker (>=2.237.0,<3.0.0)
Requires-Dist: typer (==0.15.3)
